bayesian_multitarget_latent_factors/HMC_helper.py
bayesian_multitarget_latent_factors/__init__.py
bayesian_multitarget_latent_factors/dataset_generator_toolbox.py
bayesian_multitarget_latent_factors/model.stan
bayesian_multitarget_latent_factors/model_missing_slice.stan
bayesian_multitarget_latent_factors/model_moore_penrose_trick.stan
bayesian_multitarget_latent_factors/multitarget_latent_factor_model.py
bayesian_multitarget_latent_factors/plotting_tools.py
bayesian_multitarget_latent_factors/varimax_toolbox.py
bayesian_multitarget_latent_factors-0.8.1.dist-info/LICENSE
bayesian_multitarget_latent_factors-0.8.1.dist-info/METADATA
bayesian_multitarget_latent_factors-0.8.1.dist-info/NOTICE
bayesian_multitarget_latent_factors-0.8.1.dist-info/WHEEL
bayesian_multitarget_latent_factors-0.8.1.dist-info/top_level.txt
bayesian_multitarget_latent_factors-0.8.1.dist-info/RECORD
